{
"ventana": {	"anchopx":	640,
		"altopx":	480,
		"ancho": 	150	},

"escenario": {	"ancho": 	300,
		"alto": 	100,
		"ypiso":	7,
		"zindex":	2	},

"capas": [	{	"imagen_fondo": "Images/arenas/train/0.png",
			"ancho": 200	},
		{	"imagen_fondo": "Images/arenas/train/1.png",
			"ancho": 250	},
		{	"imagen_fondo": "Images/arenas/train/2.png",
			"ancho": 300	}	],

"personaje1": {	"ancho": 	30,
		"alto": 	50,
		"nombre":	"liukang",
		"arma_speed": 2.5,
		"golpe-alto":	2,
		"golpe-bajo":	3,
		"patada-alta":	4,
		"patada-baja":	5,
		"defensa":	6,
		"arrojar":	7	},

"personaje2": {	"ancho": 	30,
		"alto": 	50,
		"nombre":	"scorpion",
		"arma_speed": 2.5,
		"golpe-alto":	0,
		"golpe-bajo":	1,
		"patada-alta":	2,
		"patada-baja":	3,
		"defensa":	4,
		"arrojar":	5	}
}
